alem/__init__.py
alem/alem.py
alem-0.0.3.dev0.dist-info/METADATA
alem-0.0.3.dev0.dist-info/WHEEL
alem-0.0.3.dev0.dist-info/entry_points.txt
alem-0.0.3.dev0.dist-info/top_level.txt
alem-0.0.3.dev0.dist-info/RECORD
